{"frames": {

"intro_00.png":
{
	"frame": {"x":119,"y":1,"w":48,"h":58},
	"rotated": false,
	"trimmed": false,
	"spriteSourceSize": {"x":0,"y":0,"w":48,"h":58},
	"sourceSize": {"w":48,"h":58}
},
"intro_01.png":
{
	"frame": {"x":261,"y":56,"w":42,"h":51},
	"rotated": false,
	"trimmed": false,
	"spriteSourceSize": {"x":0,"y":0,"w":42,"h":51},
	"sourceSize": {"w":42,"h":51}
},
"intro_02.png":
{
	"frame": {"x":160,"y":120,"w":49,"h":54},
	"rotated": false,
	"trimmed": false,
	"spriteSourceSize": {"x":0,"y":0,"w":49,"h":54},
	"sourceSize": {"w":49,"h":54}
},
"intro_03.png":
{
	"frame": {"x":119,"y":61,"w":36,"h":58},
	"rotated": false,
	"trimmed": false,
	"spriteSourceSize": {"x":0,"y":0,"w":36,"h":58},
	"sourceSize": {"w":36,"h":58}
},
"intro_04.png":
{
	"frame": {"x":201,"y":60,"w":58,"h":53},
	"rotated": false,
	"trimmed": false,
	"spriteSourceSize": {"x":0,"y":0,"w":58,"h":53},
	"sourceSize": {"w":58,"h":53}
},
"intro_05.png":
{
	"frame": {"x":146,"y":181,"w":54,"h":55},
	"rotated": false,
	"trimmed": false,
	"spriteSourceSize": {"x":0,"y":0,"w":54,"h":55},
	"sourceSize": {"w":54,"h":55}
},
"intro_06.png":
{
	"frame": {"x":129,"y":121,"w":29,"h":58},
	"rotated": false,
	"trimmed": false,
	"spriteSourceSize": {"x":0,"y":0,"w":29,"h":58},
	"sourceSize": {"w":29,"h":58}
},
"left_crouch.png":
{
	"frame": {"x":298,"y":200,"w":37,"h":47},
	"rotated": false,
	"trimmed": false,
	"spriteSourceSize": {"x":0,"y":0,"w":37,"h":47},
	"sourceSize": {"w":37,"h":47}
},
"left_fall.png":
{
	"frame": {"x":337,"y":200,"w":37,"h":47},
	"rotated": false,
	"trimmed": false,
	"spriteSourceSize": {"x":0,"y":0,"w":37,"h":47},
	"sourceSize": {"w":37,"h":47}
},
"left_guard.png":
{
	"frame": {"x":366,"y":1,"w":48,"h":50},
	"rotated": false,
	"trimmed": false,
	"spriteSourceSize": {"x":0,"y":0,"w":48,"h":50},
	"sourceSize": {"w":48,"h":50}
},
"left_guard_active.png":
{
	"frame": {"x":202,"y":176,"w":41,"h":52},
	"rotated": false,
	"trimmed": false,
	"spriteSourceSize": {"x":0,"y":0,"w":41,"h":52},
	"sourceSize": {"w":41,"h":52}
},
"left_jump.png":
{
	"frame": {"x":1,"y":1,"w":36,"h":62},
	"rotated": false,
	"trimmed": false,
	"spriteSourceSize": {"x":0,"y":0,"w":36,"h":62},
	"sourceSize": {"w":36,"h":62}
},
"left_jump_guard.png":
{
	"frame": {"x":34,"y":192,"w":38,"h":60},
	"rotated": false,
	"trimmed": false,
	"spriteSourceSize": {"x":0,"y":0,"w":38,"h":60},
	"sourceSize": {"w":38,"h":60}
},
"left_jump_guard_active.png":
{
	"frame": {"x":1,"y":129,"w":31,"h":62},
	"rotated": false,
	"trimmed": false,
	"spriteSourceSize": {"x":0,"y":0,"w":31,"h":62},
	"sourceSize": {"w":31,"h":62}
},
"left_jump_xhit_00.png":
{
	"frame": {"x":407,"y":104,"w":70,"h":36},
	"rotated": false,
	"trimmed": false,
	"spriteSourceSize": {"x":0,"y":0,"w":70,"h":36},
	"sourceSize": {"w":70,"h":36}
},
"left_jump_xhit_01.png":
{
	"frame": {"x":415,"y":180,"w":66,"h":36},
	"rotated": false,
	"trimmed": false,
	"spriteSourceSize": {"x":0,"y":0,"w":66,"h":36},
	"sourceSize": {"w":66,"h":36}
},
"left_radarmode.png":
{
	"frame": {"x":97,"y":123,"w":30,"h":59},
	"rotated": false,
	"trimmed": false,
	"spriteSourceSize": {"x":0,"y":0,"w":30,"h":59},
	"sourceSize": {"w":30,"h":59}
},
"left_stand_00.png":
{
	"frame": {"x":79,"y":1,"w":38,"h":59},
	"rotated": false,
	"trimmed": false,
	"spriteSourceSize": {"x":0,"y":0,"w":38,"h":59},
	"sourceSize": {"w":38,"h":59}
},
"left_stand_01.png":
{
	"frame": {"x":74,"y":192,"w":38,"h":60},
	"rotated": false,
	"trimmed": false,
	"spriteSourceSize": {"x":0,"y":0,"w":38,"h":60},
	"sourceSize": {"w":38,"h":60}
},
"left_xhit_00.png":
{
	"frame": {"x":157,"y":61,"w":42,"h":57},
	"rotated": false,
	"trimmed": false,
	"spriteSourceSize": {"x":0,"y":0,"w":42,"h":57},
	"sourceSize": {"w":42,"h":57}
},
"left_xhit_01.png":
{
	"frame": {"x":213,"y":1,"w":43,"h":53},
	"rotated": false,
	"trimmed": false,
	"spriteSourceSize": {"x":0,"y":0,"w":43,"h":53},
	"sourceSize": {"w":43,"h":53}
},
"left_xhit_02.png":
{
	"frame": {"x":303,"y":1,"w":61,"h":50},
	"rotated": false,
	"trimmed": false,
	"spriteSourceSize": {"x":0,"y":0,"w":61,"h":50},
	"sourceSize": {"w":61,"h":50}
},
"right_crouch.png":
{
	"frame": {"x":368,"y":53,"w":41,"h":45},
	"rotated": false,
	"trimmed": false,
	"spriteSourceSize": {"x":0,"y":0,"w":41,"h":45},
	"sourceSize": {"w":41,"h":45}
},
"right_fall.png":
{
	"frame": {"x":376,"y":200,"w":37,"h":47},
	"rotated": false,
	"trimmed": false,
	"spriteSourceSize": {"x":0,"y":0,"w":37,"h":47},
	"sourceSize": {"w":37,"h":47}
},
"right_guard.png":
{
	"frame": {"x":416,"y":52,"w":48,"h":50},
	"rotated": false,
	"trimmed": false,
	"spriteSourceSize": {"x":0,"y":0,"w":48,"h":50},
	"sourceSize": {"w":48,"h":50}
},
"right_guard_active.png":
{
	"frame": {"x":211,"y":115,"w":41,"h":52},
	"rotated": false,
	"trimmed": false,
	"spriteSourceSize": {"x":0,"y":0,"w":41,"h":52},
	"sourceSize": {"w":41,"h":52}
},
"right_jump.png":
{
	"frame": {"x":1,"y":65,"w":36,"h":62},
	"rotated": false,
	"trimmed": false,
	"spriteSourceSize": {"x":0,"y":0,"w":36,"h":62},
	"sourceSize": {"w":36,"h":62}
},
"right_jump_guard.png":
{
	"frame": {"x":39,"y":1,"w":38,"h":60},
	"rotated": false,
	"trimmed": false,
	"spriteSourceSize": {"x":0,"y":0,"w":38,"h":60},
	"sourceSize": {"w":38,"h":60}
},
"right_jump_guard_active.png":
{
	"frame": {"x":1,"y":193,"w":31,"h":62},
	"rotated": false,
	"trimmed": false,
	"spriteSourceSize": {"x":0,"y":0,"w":31,"h":62},
	"sourceSize": {"w":31,"h":62}
},
"right_jump_xhit_00.png":
{
	"frame": {"x":407,"y":142,"w":70,"h":36},
	"rotated": false,
	"trimmed": false,
	"spriteSourceSize": {"x":0,"y":0,"w":70,"h":36},
	"sourceSize": {"w":70,"h":36}
},
"right_jump_xhit_01.png":
{
	"frame": {"x":415,"y":218,"w":66,"h":36},
	"rotated": false,
	"trimmed": false,
	"spriteSourceSize": {"x":0,"y":0,"w":66,"h":36},
	"sourceSize": {"w":66,"h":36}
},
"right_radarmode.png":
{
	"frame": {"x":114,"y":184,"w":30,"h":59},
	"rotated": false,
	"trimmed": false,
	"spriteSourceSize": {"x":0,"y":0,"w":30,"h":59},
	"sourceSize": {"w":30,"h":59}
},
"right_stand_00.png":
{
	"frame": {"x":79,"y":62,"w":38,"h":59},
	"rotated": false,
	"trimmed": false,
	"spriteSourceSize": {"x":0,"y":0,"w":38,"h":59},
	"sourceSize": {"w":38,"h":59}
},
"right_stand_01.png":
{
	"frame": {"x":39,"y":63,"w":38,"h":60},
	"rotated": false,
	"trimmed": false,
	"spriteSourceSize": {"x":0,"y":0,"w":38,"h":60},
	"sourceSize": {"w":38,"h":60}
},
"right_xhit_00.png":
{
	"frame": {"x":169,"y":1,"w":42,"h":57},
	"rotated": false,
	"trimmed": false,
	"spriteSourceSize": {"x":0,"y":0,"w":42,"h":57},
	"sourceSize": {"w":42,"h":57}
},
"right_xhit_01.png":
{
	"frame": {"x":258,"y":1,"w":43,"h":53},
	"rotated": false,
	"trimmed": false,
	"spriteSourceSize": {"x":0,"y":0,"w":43,"h":53},
	"sourceSize": {"w":43,"h":53}
},
"right_xhit_02.png":
{
	"frame": {"x":305,"y":53,"w":61,"h":50},
	"rotated": false,
	"trimmed": false,
	"spriteSourceSize": {"x":0,"y":0,"w":61,"h":50},
	"sourceSize": {"w":61,"h":50}
},
"run_left_01.png":
{
	"frame": {"x":368,"y":100,"w":37,"h":48},
	"rotated": false,
	"trimmed": false,
	"spriteSourceSize": {"x":0,"y":0,"w":37,"h":48},
	"sourceSize": {"w":37,"h":48}
},
"run_left_02.png":
{
	"frame": {"x":245,"y":169,"w":51,"h":51},
	"rotated": false,
	"trimmed": false,
	"spriteSourceSize": {"x":0,"y":0,"w":51,"h":51},
	"sourceSize": {"w":51,"h":51}
},
"run_right_01.png":
{
	"frame": {"x":357,"y":150,"w":37,"h":48},
	"rotated": false,
	"trimmed": false,
	"spriteSourceSize": {"x":0,"y":0,"w":37,"h":48},
	"sourceSize": {"w":37,"h":48}
},
"run_right_02.png":
{
	"frame": {"x":254,"y":115,"w":51,"h":51},
	"rotated": false,
	"trimmed": false,
	"spriteSourceSize": {"x":0,"y":0,"w":51,"h":51},
	"sourceSize": {"w":51,"h":51}
},
"sense_radar_00.png":
{
	"frame": {"x":166,"y":238,"w":13,"h":13},
	"rotated": false,
	"trimmed": false,
	"spriteSourceSize": {"x":0,"y":0,"w":13,"h":13},
	"sourceSize": {"w":13,"h":13}
},
"sense_radar_01.png":
{
	"frame": {"x":146,"y":238,"w":18,"h":17},
	"rotated": false,
	"trimmed": false,
	"spriteSourceSize": {"x":0,"y":0,"w":18,"h":17},
	"sourceSize": {"w":18,"h":17}
},
"sense_radar_02.png":
{
	"frame": {"x":245,"y":222,"w":28,"h":27},
	"rotated": false,
	"trimmed": false,
	"spriteSourceSize": {"x":0,"y":0,"w":28,"h":27},
	"sourceSize": {"w":28,"h":27}
},
"sense_radar_03.png":
{
	"frame": {"x":307,"y":156,"w":37,"h":36},
	"rotated": false,
	"trimmed": false,
	"spriteSourceSize": {"x":0,"y":0,"w":37,"h":36},
	"sourceSize": {"w":37,"h":36}
},
"sense_radar_04.png":
{
	"frame": {"x":307,"y":105,"w":48,"h":49},
	"rotated": false,
	"trimmed": false,
	"spriteSourceSize": {"x":0,"y":0,"w":48,"h":49},
	"sourceSize": {"w":48,"h":49}
},
"sense_radar_05.png":
{
	"frame": {"x":34,"y":129,"w":61,"h":61},
	"rotated": false,
	"trimmed": false,
	"spriteSourceSize": {"x":0,"y":0,"w":61,"h":61},
	"sourceSize": {"w":61,"h":61}
},
"sense_radar_06.png":
{
	"frame": {"x":416,"y":1,"w":49,"h":49},
	"rotated": false,
	"trimmed": false,
	"spriteSourceSize": {"x":0,"y":0,"w":49,"h":49},
	"sourceSize": {"w":49,"h":49}
}},
"meta": {
	"app": "https://www.codeandweb.com/texturepacker",
	"version": "1.0",
	"image": "daredevil.png",
	"format": "RGBA8888",
	"size": {"w":482,"h":256},
	"scale": "1",
	"smartupdate": "$TexturePacker:SmartUpdate:e55dcb8eeaba56d51214fce29f92b49a:5ba84e80920bf6bfdf7c9ac4531bc4ce:df0c535e3a46c496cb3299e556072f05$"
}
}
